dartiq/__init__.py
dartiq/cli.py
dartiq/dartiq.py
dartiq-1.0.0.dist-info/entry_points.txt
dartiq-1.0.0.dist-info/WHEEL
dartiq-1.0.0.dist-info/METADATA
dartiq-1.0.0.dist-info/RECORD
