Metadata-Version: 2.1
Name: dartiq
Version: 1.0.0
Summary: Tool for running ARTIQ in Docker container.
Home-page: https://github.com/Technosystem-Labs/dartiq
Keywords: artiq,docker
Author: Mikołaj Sowiński
Author-email: msowinski@technosystem.com.pl
Requires-Python: >=3.6,<4.0
Classifier: Development Status :: 3 - Alpha
Classifier: Environment :: Console
Classifier: Intended Audience :: Developers
Classifier: License :: OSI Approved :: GNU Lesser General Public License v3 or later (LGPLv3+)
Classifier: Natural Language :: English
Classifier: Operating System :: POSIX :: Linux
Classifier: Programming Language :: Python
Classifier: Programming Language :: Python :: 3
Classifier: Programming Language :: Python :: 3.6
Classifier: Programming Language :: Python :: 3.7
Classifier: Programming Language :: Python :: 3.8
Project-URL: Repository, https://github.com/Technosystem-Labs/dartiq
